__init__.py
__main__.py
json_parser.py
algorithm/__init__.py
algorithm/interferometry.py
algorithm/pti.py
gui/__init__.py
gui/controller.py
gui/model.py
gui/view.py
hardware/__init__.py
hardware/laser.py
hardware/motherboard.py
hardware/serial_device.py
hardware/tec.py
minipti-1.9.3.dist-info/LICENSE
minipti-1.9.3.dist-info/METADATA
minipti-1.9.3.dist-info/WHEEL
minipti-1.9.3.dist-info/top_level.txt
minipti-1.9.3.dist-info/RECORD
