Metadata-Version: 2.1
Name: minipti
Version: 1.9.3
Summary: Provides algorithm and GUI for photo thermal interferometry and 3x3 couplers
Author-email: Jonas Bilal <jonasbilal@outlook.com>
Project-URL: Homepage, https://www.fhnw.ch/en/about-fhnw/schools/school-of-engineering/institutes/institute-for-sensors-and-electronics/aerosol-measurement-technology
Project-URL: Source, https://github.com/bilaljo/MiniPTI
Project-URL: Bug Tracker, https://github.com/bilaljo/MiniPTI/issues
Classifier: Programming Language :: Python :: 3
Classifier: License :: OSI Approved :: MIT License
Classifier: Operating System :: OS Independent
Requires-Python: >=3.9
License-File: LICENSE
Requires-Dist: numpy
Requires-Dist: scipy
Requires-Dist: pandas
Provides-Extra: algorithm
Requires-Dist: minipti ; extra == 'algorithm'
Requires-Dist: beartype ; extra == 'algorithm'
Requires-Dist: dacite ; extra == 'algorithm'
Requires-Dist: h5py ; extra == 'algorithm'
Requires-Dist: nptyping ; extra == 'algorithm'
Provides-Extra: gui
Requires-Dist: minipti[algorithm] ; extra == 'gui'
Requires-Dist: fastcrc ; extra == 'gui'
Requires-Dist: pyserial ; extra == 'gui'
Requires-Dist: PyQt5 ; extra == 'gui'
Requires-Dist: pyqtgraph ; extra == 'gui'
